CHANGES
COPYING
MANIFEST.in
README
RELEASE
ez_setup.py
setup.cfg
setup.py
formunculous/__init__.py
formunculous/admin.py
formunculous/fields.py
formunculous/forms.py
formunculous/models.py
formunculous/storage.py
formunculous/tests.py
formunculous/urls.py
formunculous/widgets.py
formunculous.egg-info/PKG-INFO
formunculous.egg-info/SOURCES.txt
formunculous.egg-info/dependency_links.txt
formunculous.egg-info/not-zip-safe
formunculous.egg-info/top_level.txt
formunculous/management/__init__.py
formunculous/management/commands/__init__.py
formunculous/management/commands/func_media_copy.py
formunculous/management/commands/func_media_symlink.py
formunculous/media/formunculous/css/apply.css
formunculous/media/formunculous/css/formunculous.css
formunculous/media/formunculous/css/smoothness/jquery-ui-1.7.2.custom.css
formunculous/media/formunculous/css/smoothness/images/ui-bg_flat_0_aaaaaa_40x100.png
formunculous/media/formunculous/css/smoothness/images/ui-bg_flat_75_ffffff_40x100.png
formunculous/media/formunculous/css/smoothness/images/ui-bg_glass_55_fbf9ee_1x400.png
formunculous/media/formunculous/css/smoothness/images/ui-bg_glass_65_ffffff_1x400.png
formunculous/media/formunculous/css/smoothness/images/ui-bg_glass_75_dadada_1x400.png
formunculous/media/formunculous/css/smoothness/images/ui-bg_glass_75_e6e6e6_1x400.png
formunculous/media/formunculous/css/smoothness/images/ui-bg_glass_95_fef1ec_1x400.png
formunculous/media/formunculous/css/smoothness/images/ui-bg_highlight-soft_75_cccccc_1x100.png
formunculous/media/formunculous/css/smoothness/images/ui-icons_222222_256x240.png
formunculous/media/formunculous/css/smoothness/images/ui-icons_2e83ff_256x240.png
formunculous/media/formunculous/css/smoothness/images/ui-icons_454545_256x240.png
formunculous/media/formunculous/css/smoothness/images/ui-icons_888888_256x240.png
formunculous/media/formunculous/css/smoothness/images/ui-icons_cd0a0a_256x240.png
formunculous/media/formunculous/flash/OFC.swf
formunculous/media/formunculous/img/arrow-down.gif
formunculous/media/formunculous/img/arrow-up.gif
formunculous/media/formunculous/img/arrow_down_blue.png
